{
    "keep": {
        "days": true,
        "amount": 2
    },
    "auditLog": "C:\\Users\\marku\\OneDrive\\Dokumente\\markus_data\\Software Development\\Visual_Studio_Projects\\OEE_Event_Driven II\\backend\\logs\\.420d900aff291d304f4e608f592d2ff9561034e1-audit.json",
    "files": [
        {
            "date": 1724234073837,
            "name": "C:\\Users\\marku\\OneDrive\\Dokumente\\markus_data\\Software Development\\Visual_Studio_Projects\\OEE_Event_Driven II\\backend\\logs\\error-2024-08-21.log",
            "hash": "bf9e6feb6616b78cc96e4e1d208771ba6c2c8ca5766555ea9c1e79c57eda0d4a"
        }
    ],
    "hashType": "sha256"
}