{
    "keep": {
        "days": true,
        "amount": 14
    },
    "auditLog": "C:\\Users\\marku\\OneDrive\\Dokumente\\markus_data\\Software Development\\Visual_Studio_Projects\\OEE_calculator\\OEE_calculator\\logs\\.f22be67120b37dc9163ce787572388cce4a95418-audit.json",
    "files": [
        {
            "date": 1720304454174,
            "name": "C:\\Users\\marku\\OneDrive\\Dokumente\\markus_data\\Software Development\\Visual_Studio_Projects\\OEE_calculator\\OEE_calculator\\logs\\rejections-2024-07-07.log",
            "hash": "8455a973e91179e18ad4bc5316d50c0b672821a187afb61e958ffb99cbc2e5de"
        },
        {
            "date": 1720470375462,
            "name": "C:\\Users\\marku\\OneDrive\\Dokumente\\markus_data\\Software Development\\Visual_Studio_Projects\\OEE_calculator\\OEE_calculator\\logs\\rejections-2024-07-08.log",
            "hash": "fac650b8126e588f7c886838a3a72829f9368b9ebd75756c6a818eef4ffa6306"
        },
        {
            "date": 1720476053972,
            "name": "C:\\Users\\marku\\OneDrive\\Dokumente\\markus_data\\Software Development\\Visual_Studio_Projects\\OEE_calculator\\OEE_calculator\\logs\\rejections-2024-07-09.log",
            "hash": "8596ae55198da1a06c8c51685cca3431565c13da1b94e1d3ca5df3867165b28b"
        },
        {
            "date": 1720562477106,
            "name": "C:\\Users\\marku\\OneDrive\\Dokumente\\markus_data\\Software Development\\Visual_Studio_Projects\\OEE_calculator\\OEE_calculator\\logs\\rejections-2024-07-10.log",
            "hash": "110f7ac931c04e3895fc6ad5b3b9224b2616a9026eb76a25c0470f4ac0c858d4"
        }
    ],
    "hashType": "sha256"
}